sparse/__init__.py
sparse/_common.py
sparse/_dok.py
sparse/_io.py
sparse/_numba_extension.py
sparse/_settings.py
sparse/_slicing.py
sparse/_sparse_array.py
sparse/_umath.py
sparse/_utils.py
sparse/_version.py
sparse/_compressed/__init__.py
sparse/_compressed/common.py
sparse/_compressed/compressed.py
sparse/_compressed/convert.py
sparse/_compressed/indexing.py
sparse/_coo/__init__.py
sparse/_coo/common.py
sparse/_coo/core.py
sparse/_coo/indexing.py
sparse/_coo/numba_extension.py
sparse/finch_backend/__init__.py
sparse/numba_backend/__init__.py
sparse/numba_backend/_common.py
sparse/numba_backend/_dok.py
sparse/numba_backend/_io.py
sparse/numba_backend/_numba_extension.py
sparse/numba_backend/_settings.py
sparse/numba_backend/_slicing.py
sparse/numba_backend/_sparse_array.py
sparse/numba_backend/_umath.py
sparse/numba_backend/_utils.py
sparse/numba_backend/_compressed/__init__.py
sparse/numba_backend/_compressed/common.py
sparse/numba_backend/_compressed/compressed.py
sparse/numba_backend/_compressed/convert.py
sparse/numba_backend/_compressed/indexing.py
sparse/numba_backend/_coo/__init__.py
sparse/numba_backend/_coo/common.py
sparse/numba_backend/_coo/core.py
sparse/numba_backend/_coo/indexing.py
sparse/numba_backend/_coo/numba_extension.py
sparse/numba_backend/tests/conftest.py
sparse/numba_backend/tests/test_array_function.py
sparse/numba_backend/tests/test_compressed.py
sparse/numba_backend/tests/test_compressed_2d.py
sparse/numba_backend/tests/test_compressed_convert.py
sparse/numba_backend/tests/test_conversion.py
sparse/numba_backend/tests/test_coo.py
sparse/numba_backend/tests/test_coo_numba.py
sparse/numba_backend/tests/test_dask_interop.py
sparse/numba_backend/tests/test_dok.py
sparse/numba_backend/tests/test_dot.py
sparse/numba_backend/tests/test_einsum.py
sparse/numba_backend/tests/test_elemwise.py
sparse/numba_backend/tests/test_io.py
sparse/numba_backend/tests/test_namespace.py
sparse/tests/conftest.py
sparse/tests/test_array_function.py
sparse-0.15.4.dist-info/LICENSE
sparse-0.15.4.dist-info/METADATA
sparse-0.15.4.dist-info/WHEEL
sparse-0.15.4.dist-info/entry_points.txt
sparse-0.15.4.dist-info/top_level.txt
sparse-0.15.4.dist-info/RECORD
