Metadata-Version: 2.1
Name: sparse
Version: 0.15.4
Summary: Sparse n-dimensional arrays for the PyData ecosystem
Maintainer-email: Hameer Abbasi <hameerabbasi@yahoo.com>
License: BSD 3-Clause License
Project-URL: Documentation, https://sparse.pydata.org/
Project-URL: Source, https://github.com/pydata/sparse/
Project-URL: Repository, https://github.com/pydata/sparse.git
Project-URL: Issue Tracker, https://github.com/pydata/sparse/issues
Project-URL: Discussions, https://github.com/pydata/sparse/discussions
Keywords: sparse,numpy,scipy,dask
Classifier: Development Status :: 2 - Pre-Alpha
Classifier: Operating System :: OS Independent
Classifier: License :: OSI Approved :: BSD License
Classifier: Programming Language :: Python
Classifier: Programming Language :: Python :: 3
Classifier: Programming Language :: Python :: 3.8
Classifier: Programming Language :: Python :: 3.9
Classifier: Programming Language :: Python :: 3.10
Classifier: Programming Language :: Python :: 3.11
Classifier: Programming Language :: Python :: 3 :: Only
Classifier: Intended Audience :: Developers
Classifier: Intended Audience :: Science/Research
Requires-Python: >=3.8
License-File: LICENSE
Requires-Dist: numpy>=1.17
Requires-Dist: scipy>=0.19
Requires-Dist: numba>=0.49
Provides-Extra: docs
Requires-Dist: sphinx; extra == "docs"
Requires-Dist: sphinx_rtd_theme; extra == "docs"
Provides-Extra: tests
Requires-Dist: dask[array]; extra == "tests"
Requires-Dist: pytest>=3.5; extra == "tests"
Requires-Dist: pytest-cov; extra == "tests"
Requires-Dist: pre-commit; extra == "tests"
Provides-Extra: tox
Requires-Dist: sparse[tests]; extra == "tox"
Requires-Dist: tox; extra == "tox"
Provides-Extra: all
Requires-Dist: sparse[docs,tox]; extra == "all"
Requires-Dist: matrepr; extra == "all"
